rdfind2.py
rdfind2-0.1.5.dist-info/METADATA
rdfind2-0.1.5.dist-info/WHEEL
rdfind2-0.1.5.dist-info/entry_points.txt
rdfind2-0.1.5.dist-info/RECORD
