Metadata-Version: 2.1
Name: rdfind2
Version: 0.1.5
Summary: Find duplicated files very fast
License: MIT
Author: trim21
Author-email: trim21.me@gmail.com
Requires-Python: >=3.9,<4.0
Classifier: License :: OSI Approved :: MIT License
Classifier: Programming Language :: Python :: 3
Classifier: Programming Language :: Python :: 3.9
Classifier: Programming Language :: Python :: 3.10
Classifier: Programming Language :: Python :: 3.11
Requires-Dist: click (>=8,<9)
Requires-Dist: tqdm (>=4.65.0,<5.0.0)
